Metadata-Version: 1.1
Name: CaculatorOfWolfs
Version: 0.0.3
Summary: A calculator
Home-page: UNKNOWN
Author: Wolfuri
Author-email: UNKNOWN
License: MIT
Keywords: calc
Platform: UNKNOWN
Classifier: Development Status :: 5 - Production/Stable
Classifier: Intended Audience :: Education
Classifier: Operating System :: Microsoft :: Windows :: Windows 10
Classifier: License :: OSI Approved :: MIT License
Classifier: Programming Language :: Python :: 3
